<Vehicle name="MH60_Blackhawk">
 <Physics pushable="0">
  <Buoyancy waterDensity="150" waterResistance="2500"/>
  <Simulation maxTimeStep="0.02" minEnergy="0.16" maxLoggedCollisions="2"/>
 </Physics>
 <Damages submergedRatioMax="0.40000001" submergedDamageMult="20" collDamageThreshold="10" groundCollisionMinMult="2" groundCollisionMaxMult="5" groundCollisionMinSpeed="3" groundCollisionMaxSpeed="60" >
  <DamageMultipliers>
   <DamageMultiplier damageType="bullet" multiplier="0.02" id="idbulletmult"/>
   <DamageMultiplier damageType="melee" multiplier="0"/>
   <DamageMultiplier damageType="collision" multiplier="0.5"/>
   <DamageMultiplier damageType="rocket" multiplier="10"/>
  </DamageMultipliers>
  <DamagesGroups>
   <DamagesGroup name="Destroy" useTemplate="VehicleDestroy">
    <DamagesSubGroups>
     <DamagesSubGroup delay="0" randomness="1">
      <DamageBehaviors>
       <DamageBehavior class="Explosion">
         <Explosion damage="2500" helper="engineSmokeOut" pressure="3000" radius="10" minRadius="5" physRadius="3" minPhysRadius="2.2" />
       </DamageBehavior>
      </DamageBehaviors>
     </DamagesSubGroup>
    </DamagesSubGroups>
   </DamagesGroup>
   <DamagesGroup name="DestroyEngine">
    <DamagesSubGroups>
     <DamagesSubGroup delay="0" randomness="0">
      <DamageBehaviors>
       <DamageBehavior class="MovementNotification">
        <MovementNotification isDamageAlwaysFull="1"/>
       </DamageBehavior>
       <DamageBehavior class="CameraShake">
        <CameraShake />
       </DamageBehavior>
      </DamageBehaviors>
     </DamagesSubGroup>
    </DamagesSubGroups>
   </DamagesGroup>
  </DamagesGroups>
 </Damages>
 <Components>
  <Component name="BackRotor" damageMax="150" major="1" minBound="-1.6001,-11.939,1.7024" maxBound="1.6001,-08.5796,5.3024001" useBoundsFromParts="0" hullAffection="1" id="idBackRotor">
   <DamageMultipliers>
    <DamageMultiplier damageType="bullet" multiplier="0.1"/>
    <DamageMultiplier damageType="melee" multiplier="0.0"/>
    <DamageMultiplier damageType="collision" multiplier="0.5"/>
   </DamageMultipliers>
   <DamageBehaviors>
    <DamageBehavior class="Effect" damageRatioMin="0.25" damageRatioMax="0.5">
     <Effect effect="BackRotorDamaged" disableAfterExplosion="1"/>
    </DamageBehavior>
    <DamageBehavior class="Effect" damageRatioMin="0.5">
     <Effect effect="BackRotorExplosion" disableAfterExplosion="1"/>
    </DamageBehavior>
    <DamageBehavior class="MovementNotification" damageRatioMin="1">
     <MovementNotification isSteering="1"/>
    </DamageBehavior>
    <DamageBehavior class="AISignal" damageRatioMin="1" ignoreVehicleDestruction="1">
     <AISignal signalId="1" signalText="TO_HELI_EMERGENCYLANDING"/>
    </DamageBehavior>
   </DamageBehaviors>
  </Component>
  <Component name="Engine" damageMax="200" major="1" minBound="-1.75,-3.0576,2.0325999" maxBound="1.75,1.9277,3.6919" useBoundsFromParts="0" hullAffection="1" id="idRotor">
   <DamageMultipliers>
    <DamageMultiplier damageType="bullet" multiplier="0.02"/>
    <DamageMultiplier damageType="melee" multiplier="0.0"/>
   </DamageMultipliers>
   <DamageBehaviors>
    <DamageBehavior class="Group" damageRatioMin="1">
     <Group name="DestroyEngine"/>
    </DamageBehavior>
    <DamageBehavior class="Effect" damageRatioMin="0.1" damageRatioMax="0.5">
     <Effect effect="EngineDamaged25" disableAfterExplosion="1"/>
    </DamageBehavior>
    <DamageBehavior class="Effect" damageRatioMin="0.5" damageRatioMax="1">
     <Effect effect="EngineDamaged75" disableAfterExplosion="1"/>
    </DamageBehavior>
   </DamageBehaviors>
  </Component>
  <Component name="Hull" damageMax="1000" major="1" minBound="-8.8309450,-14.015456,-0.94689238" maxBound="9.0925131,8.9827299,5.4283361" useBoundsFromParts="0" id="idHull">
   <DamageBehaviors>
    <DamageBehavior class="Group" damageRatioMin="1">
     <Group name="Destroy"/>
    </DamageBehavior>
    <DamageBehavior class="Group" damageRatioMin="1">
     <Group name="DestroyEngine"/>
    </DamageBehavior>
    <DamageBehavior class="Effect" damageRatioMin="0.1" damageRatioMax="0.5" ignoreVehicleDestruction="1">
     <Effect effect="HullDamaged25"/>
    </DamageBehavior>
    <DamageBehavior class="Effect" damageRatioMin="0.5" damageRatioMax="1" ignoreVehicleDestruction="1">
     <Effect effect="HullDamaged75"/>
    </DamageBehavior>
   </DamageBehaviors>
  </Component>
  <Component name="Cockpit" damageMax="0" major="1" minBound="0,0,0" maxBound="0,0,0" useBoundsFromParts="0" hullAffection="1">
   <DamageBehaviors />
  </Component>
  <Component name="RotorTails" damageMax="100" major="0" minBound="-9.4877005,-9.1875,3.0402999" maxBound="9.4856997,8.0595999,3.9052999" useBoundsFromParts="0" hullAffection="1" id="idRotor">
   <DamageMultipliers>
    <DamageMultiplier damageType="collision" multiplier="1"/>
   </DamageMultipliers>
   <DamageBehaviors>
    <DamageBehavior class="Group" damageRatioMin="1">
     <Group name="Destroy"/>
    </DamageBehavior>
   </DamageBehaviors>
  </Component>
 </Components>
 <Parts>
 <Part name="body" class="Animated" mass="18000">
   <Parts>
    <Part name="hull" class="AnimatedJoint">
     <Parts>
     </Parts>
    </Part>
   </Parts>
   <Animated filename="Objects/Vehicles/MH60_Blackhawk/MH60.cga" filenameDestroyed="Objects/Vehicles/MH60_Blackhawk/MH60_damaged.cga" id="idCGAFilename"/>
  </Part>
  <Part name="tailRotorLightRed" class="Light" helper="tailLightRed">
   <Light type="HeliRedFlash"/>
  </Part>
  <Part name="tailRotorLightWhite" class="Light" helper="tailLightWhite">
   <Light type="HeliWhite"/>
  </Part>
  <Part name="frontLightGreen" class="Light" helper="frontLightGreen">
   <Light type="HeliGreen"/>
  </Part>
  <Part name="frontLightRed" class="Light" helper="frontLightRed">
   <Light type="HeliRed"/>
  </Part>
  <Part name="bottomLightWhite" class="Light" helper="bottomLightWhite">
   <Light type="HeliWhiteFlash"/>
  </Part>
 </Parts>
 <Helpers>
  <Helper name="pilot_sit_pos" position="-0.625,2.9,1.2945" direction="0,1,0" part="body"/>
  <Helper name="pilot_enter_pos_1" position="-8,3.2859001,0.50950003" direction="0,1,0" part="body"/>
  <Helper name="pilot_enter_pos_2" position="-1.74573,2.95679,0.281693" direction="0,1,0" part="body"/>
  <Helper name="gunner_sit_pos" position="0.625,2.9,1.2945" direction="0,1,0" part="body"/>
  <Helper name="gunner_enter_pos_1" position="8,3.2859001,0.50950003" direction="0,1,0" part="body"/>
  <Helper name="gunner_enter_pos_2" position="1.74573,2.95679,0.281693" direction="0,1,0" part="body"/>
  <Helper name="passenger_enter_helper_left_pos" position="-2.5,0,0.2" direction="0,1,0" part="body"/>
  <Helper name="passenger_enter_helper_right_pos" position="2.5,0,0.2" direction="0,1,0" part="body"/>
  <Helper name="passenger03_helper_pos" position="-0.26,1,1.2" direction="0,1,0" part="body"/>
  <Helper name="passenger04_helper_pos" position="0.26,1,1.2" direction="0,1,0" part="body"/>
  <Helper name="passenger05_helper_pos" position="-0.26,0.4,1.2" direction="0,-1,0" part="body"/>
  <Helper name="passenger06_helper_pos" position="0.26,0.4,1.2" direction="0,-1,0" part="body"/>
  <Helper name="passenger07_helper_pos" position="-0.8,-1.15,1.2" direction="0,1,0" part="body"/>
  <Helper name="passenger08_helper_pos" position="-0.26,-1.15,1.2" direction="0,1,0" part="body"/>
  <Helper name="passenger09_helper_pos" position="0.26,-1.15,1.2" direction="0,1,0" part="body"/>
  <Helper name="passenger10_helper_pos" position="0.8,-1.15,1.2" direction="0,1,0" part="body"/>
  <Helper name="engineSmokeOut" position="0,-0.89429998,2.4389" direction="0,1,0" part="body"/>
  <Helper name="rotorSmokeOut" position="0,-12.178,3.9584999" direction="0,1,0" part="body"/>
  <Helper name="engine_exhaust_left" position="-1.22,-2.50391,2.5485" direction="0,-0.90609,-0.423" part="body"/>
  <Helper name="engine_exhaust_right" position="1.22,-2.50391,2.5485" direction="0,-0.9659,-0.259" part="body"/>
  <Helper name="wind_emitter" position="0,0,6.5885" direction="0,1,0" part="body"/>
  <Helper name="burningPos" position="0,-3.0548999,1.2778" direction="0,1,0" part="body"/>
  <Helper name="frontLightRed" position="-1.4965,2.1415,0.64960003" direction="-0.99620003,0.087200001,0" part="body"/>
  <Helper name="frontLightGreen" position="1.4993,2.1415,0.64960003" direction="1,0,0" part="body"/>
  <Helper name="tailLightWhite" position="-0.0055999998,-11.1232,3.9351001" direction="0,-1,0" part="body"/>
  <Helper name="tailLightRed" position="0.0082,-10.4493,4.2666998" direction="0,0,1" part="body"/>
  <Helper name="bottomLightWhite" position="0.0015,-5.6501999,0.5722" direction="0,0,-1" part="body"/>
</Helpers>
 <Actions>
 </Actions>
 <Seats>
  <Seat name="pilot" part="" enterHelper="pilot_enter_pos_2" exitHelper="pilot_enter_pos_2" sitHelper="pilot_sit_pos" isDriver="1" isPassengerShielded="1" AimPart="" seatGroupIndex="1" remotelyUseActionsFromSeat="" blurMult="0" id="idSeatPilot" actionMap="helicopter">
   <Views>
	<View class="ActionThirdPerson" canRotate="0">
     <ActionThirdPerson cameraPosOffset="0,2,1" cameraAimOffset="0,0,0" lagSpeed="5" velocityMult="0.009,0.009,0.009"/>
    </View>
    <View class="FirstPerson" canRotate="0" rotationMin="-20,0,-80" rotationMax="10,0,80" hideplayer="1">
     <FirstPerson offset="0,-0.5,0"/>
    </View>
   </Views>
   <SeatActions>
    <SeatAction class="Lights">
     <Lights activation="toggle">
      <LightParts>
       <LightPart value="tailRotorLightRed"/>
       <LightPart value="tailRotorLightWhite"/>
       <LightPart value="frontLightGreen"/>
       <LightPart value="frontLightRed"/>
	   <LightPart value="bottomLightWhite"/>
      </LightParts>
     </Lights>
    </SeatAction>
   </SeatActions>
   <Sounds inout="0" mood="1"/>
  </Seat>
  <Seat name="gunner" part="" enterHelper="gunner_enter_pos_2" exitHelper="gunner_enter_pos_2" sitHelper="gunner_sit_pos" isDriver="0" AimPart="" seatGroupIndex="2">
   <Views>
    <View class="FirstPerson" canRotate="1" rotationMin="-45,0,-70" rotationMax="25,0,70">
     <FirstPerson helper=""/>
    </View>
   </Views>
   <SeatActions />
   <Sounds inout="0" mood="1"/>
  </Seat>
  <Seat name="passengerseat3" part="" enterHelper="passenger_enter_helper_left_pos" exitHelper="passenger_enter_helper_left_pos" sitHelper="passenger03_helper_pos" isDriver="0" AimPart="" seatGroupIndex="3">
   <Views>
    <View class="FirstPerson" canRotate="1" rotationMin="-45,0,-70" rotationMax="25,0,70">
     <FirstPerson helper=""/>
    </View>
   </Views>
   <SeatActions />
   <Sounds inout="0" mood="1"/>
  </Seat>
  <Seat name="passengerseat4" part="" enterHelper="passenger_enter_helper_right_pos" exitHelper="passenger_enter_helper_right_pos" sitHelper="passenger04_helper_pos" isDriver="0" AimPart="" seatGroupIndex="3">
   <Views>
    <View class="FirstPerson" canRotate="1" rotationMin="-45,0,-70" rotationMax="25,0,70">
     <FirstPerson helper=""/>
    </View>
   </Views>
   <SeatActions />
   <Sounds inout="0" mood="1"/>
  </Seat>
  <Seat name="passengerseat5" part="" enterHelper="passenger_enter_helper_left_pos" exitHelper="passenger_enter_helper_left_pos" sitHelper="passenger05_helper_pos" isDriver="0" AimPart="" seatGroupIndex="4">
   <Views>
    <View class="FirstPerson" canRotate="1" rotationMin="-45,0,-70" rotationMax="25,0,70">
     <FirstPerson helper=""/>
    </View>
   </Views>
   <SeatActions />
   <Sounds inout="0" mood="1"/>
  </Seat>
  <Seat name="passengerseat6" part="" enterHelper="passenger_enter_helper_right_pos" exitHelper="passenger_enter_helper_right_pos" sitHelper="passenger06_helper_pos" isDriver="0" AimPart="" seatGroupIndex="4">
   <Views>
    <View class="FirstPerson" canRotate="1" rotationMin="-45,0,-70" rotationMax="25,0,70">
     <FirstPerson helper=""/>
    </View>
   </Views>
   <SeatActions />
   <Sounds inout="0" mood="1"/>
  </Seat>
  <Seat name="passengerseat7" part="" enterHelper="passenger_enter_helper_left_pos" exitHelper="passenger_enter_helper_left_pos" sitHelper="passenger07_helper_pos" isDriver="0" AimPart="" seatGroupIndex="5">
   <Views>
    <View class="FirstPerson" canRotate="1" rotationMin="-45,0,-70" rotationMax="25,0,70">
     <FirstPerson helper=""/>
    </View>
   </Views>
   <SeatActions />
   <Sounds inout="0" mood="1"/>
  </Seat>
  <Seat name="passengerseat8" part="" enterHelper="passenger_enter_helper_left_pos" exitHelper="passenger_enter_helper_left_pos" sitHelper="passenger08_helper_pos" isDriver="0" AimPart="" seatGroupIndex="5">
   <Views>
    <View class="FirstPerson" canRotate="1" rotationMin="-45,0,-70" rotationMax="25,0,70">
     <FirstPerson helper=""/>
    </View>
   </Views>
   <SeatActions />
   <Sounds inout="0" mood="1"/>
  </Seat>
  <Seat name="passengerseat9" part="" enterHelper="passenger_enter_helper_right_pos" exitHelper="passenger_enter_helper_right_pos" sitHelper="passenger09_helper_pos" isDriver="0" AimPart="" seatGroupIndex="5">
   <Views>
    <View class="FirstPerson" canRotate="1" rotationMin="-45,0,-70" rotationMax="25,0,70">
     <FirstPerson helper=""/>
    </View>
   </Views>
   <SeatActions />
   <Sounds inout="0" mood="1"/>
  </Seat>
  <Seat name="passengerseat10" part="" enterHelper="passenger_enter_helper_right_pos" exitHelper="passenger_enter_helper_right_pos" sitHelper="passenger10_helper_pos" isDriver="0" AimPart="" seatGroupIndex="5">
   <Views>
    <View class="FirstPerson" canRotate="1" rotationMin="-45,0,-70" rotationMax="25,0,70">
     <FirstPerson helper=""/>
    </View>
   </Views>
   <SeatActions />
   <Sounds inout="0" mood="1"/>
  </Seat>
 </Seats>
 <MovementParams>
  <Helicopter
	  engineWarmupDelay="3"
	  enginePowerMax="2"
	  rotationDamping="20"
	  altitudeMax="500"
	  rotorDiskTiltScale="0.44999999"
	  pitchResponsiveness="19"
	  rollResponsiveness="18"
	  yawResponsiveness="29"
	  maxYawRate="3.142"
	  maxFwdSpeed="10"
	  maxLeftSpeed="10"
	  maxSpeed="10"
	  maxUpSpeed="10"
	  velDamping="0.3"
	  basicSpeedFraction="0.69999999"
	  yawDecreaseWithSpeed="12"
	  tiltPerVelDifference="0.039999999"
	  maxTiltAngle="0.55000001"
	  maxRollAngle="60"
	  extraRollForTurn="0.5"
	  rollForTurnForce="0.5"
	  yawPerRoll="-0.1"
	  pitchActionPerTilt="5"
	  pitchInputConst="3"
	  powerInputConst="1"
	  powerInputDamping="-0.75"
	  relaxForce="2"
	  yawInputConst="4"
	  yawInputDamping="-0.5">
   <Animations engine="rotor"/>
   <SoundParams engineSoundPosition="engineSmokeOut" runSoundDelay="1.8" rpmPitchSpeed="1.2"/>
  </Helicopter>
 </MovementParams>
 <Particles mfxRow="vfx_Helicopter">
  <Exhaust insideWater="0" outsideWater="1">
   <Helpers>
    <Helper value="engine_exhaust_left"/>
    <Helper value="engine_exhaust_right"/>
   </Helpers>
   <EngineStart effect="Vehicles.MH60_BlackHawk.Engine.Start"/>
   <EngineStop effect="Vehicles.MH60_BlackHawk.Engine.Stop"/>
   <EngineRunning 
		effect="Vehicles.MH60_BlackHawk.Engine.Running" 
		boostEffect="Vehicles.MH60_BlackHawk.Engine.Boost" 
		baseSizeScale="1" 
		minSpeed="0" 
		minSpeedSizeScale="1" 
		minSpeedCountScale="1" 
		minSpeedSpeedScale="1" 
		maxSpeed="20" 
		maxSpeedSizeScale="1" 
		maxSpeedCountScale="1" 
		maxSpeedSpeedScale="1" 
		minPower="0" 
		minPowerSizeScale="1" 
		minPowerCountScale="1" 
		minPowerSpeedScale="1" 
		maxPower="1" 
		maxPowerSizeScale="1" 
		maxPowerCountScale="1" 
		maxPowerSpeedScale="1"/>
  </Exhaust>
  <DamageEffects>
   <DamageEffect name="EngineDamaged25" helper="engineSmokeOut" effect="Vehicles.MH60_BlackHawk.Damage.Engine_25"/>
   <DamageEffect name="EngineDamaged75" helper="engineSmokeOut" effect="Vehicles.MH60_BlackHawk.Damage.Engine_75" scaleMax="1" gravityDirection="0,0,1" pulsePeriod="0"/>
   <DamageEffect name="HullDamaged25" helper="burningPos" effect="Vehicles.MH60_BlackHawk.Damage.Hull_25" scaleMax="1" gravityDirection="0,0,1" pulsePeriod="0"/>
   <DamageEffect name="HullDamaged75" helper="burningPos" effect="Vehicles.MH60_BlackHawk.Damage.Hull_75" scaleMax="1" gravityDirection="0,0,1" pulsePeriod="0"/>
   <DamageEffect name="VehicleDestroyed" helper="burningPos" effect="Vehicles.MH60_BlackHawk.Damage.Destroyed"/>
   <DamageEffect name="RotorDamaged" helper="Rotor" effect="Vehicles.MH60_BlackHawk.Damage.RotorDamaged"/>
   <DamageEffect name="RotorExplosion" helper="Rotor" effect="Vehicles.MH60_BlackHawk.Damage.RotorDestroyed"/>
   <DamageEffect name="BackRotorDamaged" helper="BackRotor" effect="Vehicles.MH60_BlackHawk.Damage.TailRotorDamaged"/>
   <DamageEffect name="BackRotorExplosion" helper="BackRotor" effect="Vehicles.MH60_BlackHawk.Damage.TailRotorDestroyed"/>
   </DamageEffects>
  <EnvironmentLayers>
   <EnvironmentLayer
	   minSpeed="0"
	   minSpeedSizeScale="1"
	   minSpeedCountScale="1"
	   minSpeedSpeedScale="1"
	   maxSpeed="10"
	   maxSpeedSizeScale="1"
	   maxSpeedCountScale="1"
	   maxSpeedSpeedScale="1"
	   minPowerSizeScale="0.5"
	   minPowerCountScale="0.5"
	   maxPowerSizeScale="1"
	   maxPowerCountScale="1">
    <Alignment alignGroundHeight="35" maxHeightSizeScale="1" maxHeightCountScale="1" alignToWater="0"/>
    <Emitters />
    <Wheels />
   </EnvironmentLayer>
  </EnvironmentLayers>
 </Particles>
 <Animations>
  <Animation name="rotor" part="body">
   <States>
    <State name="default" animation="rotate" soundHelper="rotorSmokeOut" isLooped="1" speedDefault="0" speedMin="0.05" speedMax="1.0" id="idRotorAnim">
     <Materials>
      <Material name="rotor_main" setting="opacity" invertValue="1"/>
      <Material name="rotor_main_blending" setting="opacity" invertValue="0"/>
     </Materials>
    </State>
   </States>
  </Animation>
 </Animations>
</Vehicle>